citrusdb/__init__.py
citrusdb/api/__init__.py
citrusdb/api/console.py
citrusdb/api/index.py
citrusdb/api/local.py
citrusdb/db/__init__.py
citrusdb/db/index/__init__.py
citrusdb/db/index/hnswlib.py
citrusdb/db/postgres/db.py
citrusdb/db/postgres/queries.py
citrusdb/db/postgres/query_builder.py
citrusdb/db/sqlite/__init__.py
citrusdb/db/sqlite/db.py
citrusdb/db/sqlite/queries.py
citrusdb/db/sqlite/query_builder.py
citrusdb/embedding/__init__.py
citrusdb/embedding/openai.py
citrusdb/embedding/utils.py
citrusdb/utils/__init__.py
citrusdb/utils/types.py
citrusdb/utils/utils.py
cloud-temp/__init__.py
cloud-temp/index.py
cloud-temp/main-pg.py
citrusdb-0.6.9.dist-info/LICENSE
citrusdb-0.6.9.dist-info/METADATA
citrusdb-0.6.9.dist-info/WHEEL
citrusdb-0.6.9.dist-info/top_level.txt
citrusdb-0.6.9.dist-info/RECORD
