Metadata-Version: 2.1
Name: citrusdb
Version: 0.6.9
Summary: open-source vector database. store and retrieve embeddings for your next ai project!
Home-page: https://github.com/0xDebabrata/citrus
Author: Debabrata Mondal
Author-email: Debabrata Mondal <debabrata.js@protonmail.com>
Project-URL: Homepage, https://github.com/0xDebabrata/citrus
Classifier: Programming Language :: Python :: 3
Classifier: License :: OSI Approved :: Apache Software License
Classifier: Operating System :: OS Independent
Requires-Python: >=3.7
License-File: LICENSE
Requires-Dist: hnswlib >=0.7
Requires-Dist: numpy >=1.21.6
Requires-Dist: openai >=0.27
Requires-Dist: psycopg[c] >=3.1.9
Requires-Dist: psycopg[pool] >=3.1.7
